autoreduce/__init__.py
autoreduce/converters.py
autoreduce/local_sensitivity.py
autoreduce/model_reduction.py
autoreduce/ode.py
autoreduce/sbmlutil.py
autoreduce/system.py
autoreduce/utils.py
autoreduce-0.3.0.dist-info/METADATA
autoreduce-0.3.0.dist-info/WHEEL
autoreduce-0.3.0.dist-info/licenses/LICENSE
autoreduce-0.3.0.dist-info/RECORD
