Metadata-Version: 2.4
Name: autoreduce
Version: 0.3.0
Summary: Python based automated model reduction tools for SBML models
Project-URL: Documentation, https://autoreduce.readthedocs.io
Project-URL: Source, https://github.com/ayush9pandey/AutoReduce
Project-URL: Tracker, https://github.com/ayush9pandey/AutoReduce/issues
Author-email: Ayush Pandey <ayushpandey@ucmerced.edu>
License: BSD 3-Clause License
License-File: LICENSE
Keywords: Automated Model Reduction,Hill functions,Modeling,QSSA,SBML
Requires-Python: >=3.9
Requires-Dist: numpy
Requires-Dist: python-libsbml
Requires-Dist: scipy
Requires-Dist: sympy
Provides-Extra: all
Requires-Dist: matplotlib; extra == 'all'
Requires-Dist: seaborn; extra == 'all'
Provides-Extra: test
Requires-Dist: pytest; extra == 'test'
Requires-Dist: pytest-cov; extra == 'test'
Requires-Dist: pytest-xdist; extra == 'test'
